bardi/__init__.py
bardi/pipeline.py
bardi/data/__init__.py
bardi/data/data_handlers.py
bardi/data/utils/__init__.py
bardi/data/utils/pyarrow_utils.py
bardi/nlp_engineering/__init__.py
bardi/nlp_engineering/embedding_generator.py
bardi/nlp_engineering/label_processor.py
bardi/nlp_engineering/normalizer.py
bardi/nlp_engineering/pre_tokenizer.py
bardi/nlp_engineering/splitter.py
bardi/nlp_engineering/tokenizer_encoder.py
bardi/nlp_engineering/tokenizer_trainer.py
bardi/nlp_engineering/vocab_encoder.py
bardi/nlp_engineering/regex_library/__init__.py
bardi/nlp_engineering/regex_library/pathology_report.py
bardi/nlp_engineering/regex_library/regex_lib.py
bardi/nlp_engineering/regex_library/regex_set.py
bardi/nlp_engineering/utils/__init__.py
bardi/nlp_engineering/utils/helper_utils.py
bardi/nlp_engineering/utils/polars_utils.py
bardi/nlp_engineering/utils/tokenizers_lib.py
bardi/nlp_engineering/utils/validations.py
bardi-0.5.0.dist-info/LICENSE
bardi-0.5.0.dist-info/METADATA
bardi-0.5.0.dist-info/WHEEL
bardi-0.5.0.dist-info/top_level.txt
bardi-0.5.0.dist-info/RECORD
