Metadata-Version: 2.1
Name: bardi
Version: 0.5.0
Summary: A flexible machine learning data pre-processing pipeline framework.
Author: Oak Ridge National Laboratory
Project-URL: Homepage, https://github.com/DOE-NCI-MOSSAIC/bardi
Project-URL: Documentation, https://doe-nci-mossaic.github.io/bardi/
Classifier: Programming Language :: Python :: 3 :: Only
Classifier: License :: OSI Approved :: MIT License
Requires-Python: >=3.9.0
License-File: LICENSE
Requires-Dist: duckdb==0.8.0
Requires-Dist: gensim>=4.1.2
Requires-Dist: numpy>=1.21.5
Requires-Dist: pandas>=1.4.4
Requires-Dist: polars-u64-idx[pyarrow]>=1.6
Requires-Dist: pyarrow>=14.0.1
Requires-Dist: scipy>=1.10.1
Requires-Dist: tokenizers>=0.13.3
Requires-Dist: transformers>=4.29.2
Requires-Dist: datasets>=2.12.0
